iotest.py
simple_iotest-3.61.2.dist-info/METADATA
simple_iotest-3.61.2.dist-info/WHEEL
simple_iotest-3.61.2.dist-info/entry_points.txt
simple_iotest-3.61.2.dist-info/top_level.txt
simple_iotest-3.61.2.dist-info/RECORD
