Metadata-Version: 2.4
Name: simple-iotest
Version: 3.61.2
Summary: A dead simple iotest for HPC environments
Author-email: Yufei Pan <pan@zopyr.us>
Project-URL: Homepage, https://github.com/yufei-pan/simple-iotest
Classifier: Programming Language :: Python :: 3
Classifier: Operating System :: POSIX :: Linux
Classifier: Operating System :: MacOS :: MacOS X
Classifier: Operating System :: Microsoft :: Windows
Requires-Python: >=3.6
Requires-Dist: argparse
Requires-Dist: tee-logger>=6.34
